[{"model": "auth.permission", "pk": 1, "fields": {"name": "Can add log entry", "content_type": 1, "codename": "add_logentry"}}, {"model": "auth.permission", "pk": 2, "fields": {"name": "Can change log entry", "content_type": 1, "codename": "change_logentry"}}, {"model": "auth.permission", "pk": 3, "fields": {"name": "Can delete log entry", "content_type": 1, "codename": "delete_logentry"}}, {"model": "auth.permission", "pk": 4, "fields": {"name": "Can view log entry", "content_type": 1, "codename": "view_logentry"}}, {"model": "auth.permission", "pk": 5, "fields": {"name": "Can add permission", "content_type": 3, "codename": "add_permission"}}, {"model": "auth.permission", "pk": 6, "fields": {"name": "Can change permission", "content_type": 3, "codename": "change_permission"}}, {"model": "auth.permission", "pk": 7, "fields": {"name": "Can delete permission", "content_type": 3, "codename": "delete_permission"}}, {"model": "auth.permission", "pk": 8, "fields": {"name": "Can view permission", "content_type": 3, "codename": "view_permission"}}, {"model": "auth.permission", "pk": 9, "fields": {"name": "Can add group", "content_type": 2, "codename": "add_group"}}, {"model": "auth.permission", "pk": 10, "fields": {"name": "Can change group", "content_type": 2, "codename": "change_group"}}, {"model": "auth.permission", "pk": 11, "fields": {"name": "Can delete group", "content_type": 2, "codename": "delete_group"}}, {"model": "auth.permission", "pk": 12, "fields": {"name": "Can view group", "content_type": 2, "codename": "view_group"}}, {"model": "auth.permission", "pk": 13, "fields": {"name": "Can add content type", "content_type": 4, "codename": "add_contenttype"}}, {"model": "auth.permission", "pk": 14, "fields": {"name": "Can change content type", "content_type": 4, "codename": "change_contenttype"}}, {"model": "auth.permission", "pk": 15, "fields": {"name": "Can delete content type", "content_type": 4, "codename": "delete_contenttype"}}, {"model": "auth.permission", "pk": 16, "fields": {"name": "Can view content type", "content_type": 4, "codename": "view_contenttype"}}, {"model": "auth.permission", "pk": 17, "fields": {"name": "Can add session", "content_type": 5, "codename": "add_session"}}, {"model": "auth.permission", "pk": 18, "fields": {"name": "Can change session", "content_type": 5, "codename": "change_session"}}, {"model": "auth.permission", "pk": 19, "fields": {"name": "Can delete session", "content_type": 5, "codename": "delete_session"}}, {"model": "auth.permission", "pk": 20, "fields": {"name": "Can view session", "content_type": 5, "codename": "view_session"}}, {"model": "auth.permission", "pk": 21, "fields": {"name": "Can add parent", "content_type": 6, "codename": "add_parent"}}, {"model": "auth.permission", "pk": 22, "fields": {"name": "Can change parent", "content_type": 6, "codename": "change_parent"}}, {"model": "auth.permission", "pk": 23, "fields": {"name": "Can delete parent", "content_type": 6, "codename": "delete_parent"}}, {"model": "auth.permission", "pk": 24, "fields": {"name": "Can view parent", "content_type": 6, "codename": "view_parent"}}, {"model": "auth.permission", "pk": 25, "fields": {"name": "Can add student", "content_type": 7, "codename": "add_student"}}, {"model": "auth.permission", "pk": 26, "fields": {"name": "Can change student", "content_type": 7, "codename": "change_student"}}, {"model": "auth.permission", "pk": 27, "fields": {"name": "Can delete student", "content_type": 7, "codename": "delete_student"}}, {"model": "auth.permission", "pk": 28, "fields": {"name": "Can view student", "content_type": 7, "codename": "view_student"}}, {"model": "auth.permission", "pk": 29, "fields": {"name": "Can add teacher", "content_type": 8, "codename": "add_teacher"}}, {"model": "auth.permission", "pk": 30, "fields": {"name": "Can change teacher", "content_type": 8, "codename": "change_teacher"}}, {"model": "auth.permission", "pk": 31, "fields": {"name": "Can delete teacher", "content_type": 8, "codename": "delete_teacher"}}, {"model": "auth.permission", "pk": 32, "fields": {"name": "Can view teacher", "content_type": 8, "codename": "view_teacher"}}, {"model": "auth.permission", "pk": 33, "fields": {"name": "Can add indicator", "content_type": 9, "codename": "add_indicator"}}, {"model": "auth.permission", "pk": 34, "fields": {"name": "Can change indicator", "content_type": 9, "codename": "change_indicator"}}, {"model": "auth.permission", "pk": 35, "fields": {"name": "Can delete indicator", "content_type": 9, "codename": "delete_indicator"}}, {"model": "auth.permission", "pk": 36, "fields": {"name": "Can view indicator", "content_type": 9, "codename": "view_indicator"}}, {"model": "auth.permission", "pk": 37, "fields": {"name": "Can add user", "content_type": 10, "codename": "add_customuser"}}, {"model": "auth.permission", "pk": 38, "fields": {"name": "Can change user", "content_type": 10, "codename": "change_customuser"}}, {"model": "auth.permission", "pk": 39, "fields": {"name": "Can delete user", "content_type": 10, "codename": "delete_customuser"}}, {"model": "auth.permission", "pk": 40, "fields": {"name": "Can view user", "content_type": 10, "codename": "view_customuser"}}, {"model": "contenttypes.contenttype", "pk": 1, "fields": {"app_label": "admin", "model": "logentry"}}, {"model": "contenttypes.contenttype", "pk": 2, "fields": {"app_label": "auth", "model": "group"}}, {"model": "contenttypes.contenttype", "pk": 3, "fields": {"app_label": "auth", "model": "permission"}}, {"model": "contenttypes.contenttype", "pk": 4, "fields": {"app_label": "contenttypes", "model": "contenttype"}}, {"model": "contenttypes.contenttype", "pk": 5, "fields": {"app_label": "sessions", "model": "session"}}, {"model": "contenttypes.contenttype", "pk": 6, "fields": {"app_label": "data_collection", "model": "parent"}}, {"model": "contenttypes.contenttype", "pk": 7, "fields": {"app_label": "data_collection", "model": "student"}}, {"model": "contenttypes.contenttype", "pk": 8, "fields": {"app_label": "data_collection", "model": "teacher"}}, {"model": "contenttypes.contenttype", "pk": 9, "fields": {"app_label": "indicators", "model": "indicator"}}, {"model": "contenttypes.contenttype", "pk": 10, "fields": {"app_label": "settings", "model": "customuser"}}, {"model": "sessions.session", "pk": "th9od3zvxxl30so7j3vm9sa9xild74fy", "fields": {"session_data": ".eJxVjMEOwiAQRP-FsyEFunbx6N1vIAu7laqBpLQn47_bJj3oHOe9mbcKtC45rE3mMLG6KKNOv12k9JSyA35QuVedalnmKepd0Qdt-lZZXtfD_TvI1PK2joCMdiBGcMyOyQGT7VA69BS3sCT0AJJcEjJgxuT7XuwQBYTOo_p8AQyuOVQ:1vvB6L:VoG9KTcazvmAnttbplgFrXiiaX4Nc4F9Z4B7amWjoLM", "expire_date": "2026-03-11T09:22:37.320Z"}}, {"model": "data_collection.student", "pk": 1, "fields": {"id_number": "S001", "region": "Kigoma", "district": "Kasulu", "school": "Kasulu Primary", "gender": "Male", "age_group": "13-15", "disability_status": true, "knowledge_on_violence": true, "experienced_vac": true, "forms_of_violence": "Bullying", "perpetrators": "Classmates", "vulnerable_places": "Playground", "reporting_violence": true, "effectiveness_reporting_system": "Effective"}}, {"model": "data_collection.student", "pk": 2, "fields": {"id_number": "S002", "region": "Dar Es Salaam", "district": "Kinondoni", "school": "Goba Sec", "gender": "Female", "age_group": "16-18", "disability_status": false, "knowledge_on_violence": true, "experienced_vac": false, "forms_of_violence": "Harassment", "perpetrators": "Teacher", "vulnerable_places": "Classroom", "reporting_violence": false, "effectiveness_reporting_system": "Weak"}}, {"model": "data_collection.student", "pk": 3, "fields": {"id_number": "S003", "region": "Morogoro", "district": "Morogoro", "school": "Moro Sec", "gender": "Male", "age_group": "13-15", "disability_status": true, "knowledge_on_violence": true, "experienced_vac": false, "forms_of_violence": "Toilets", "perpetrators": "Friends", "vulnerable_places": "Toilets", "reporting_violence": true, "effectiveness_reporting_system": "Weak"}}, {"model": "data_collection.student", "pk": 4, "fields": {"id_number": "S004", "region": "Tabora", "district": "Uyui", "school": "Uyuwi Sec", "gender": "Female", "age_group": "16-18", "disability_status": false, "knowledge_on_violence": true, "experienced_vac": true, "forms_of_violence": "School", "perpetrators": "Parents", "vulnerable_places": "Street", "reporting_violence": false, "effectiveness_reporting_system": "Effective"}}, {"model": "data_collection.student", "pk": 5, "fields": {"id_number": "S005", "region": "Manyara", "district": "Mburu", "school": "Manyara Sec", "gender": "Male", "age_group": "16-18", "disability_status": false, "knowledge_on_violence": false, "experienced_vac": false, "forms_of_violence": "School", "perpetrators": "Friends", "vulnerable_places": "Toilets", "reporting_violence": false, "effectiveness_reporting_system": "Weak"}}, {"model": "data_collection.teacher", "pk": 1, "fields": {"id_number": "T001", "region": "Dar Es Salaam", "district": "Ilala", "school": "School A", "gender": "Male", "age_group": "30-40", "marital_status": "Married", "education_level": "Bachelor", "forms_of_violence": "Bullying", "reporting_violence": true, "vulnerable_places": "Playground", "right_to_discipline_child": true, "effective_handling_vac": "Effective", "training_received": "Yes"}}, {"model": "data_collection.teacher", "pk": 2, "fields": {"id_number": "T002", "region": "Dar Es Salaam", "district": "Kinondoni", "school": "School B", "gender": "Female", "age_group": "25-35", "marital_status": "Single", "education_level": "Diploma", "forms_of_violence": "Harassment", "reporting_violence": false, "vulnerable_places": "Classroom", "right_to_discipline_child": false, "effective_handling_vac": "Weak", "training_received": "No"}}, {"model": "data_collection.teacher", "pk": 3, "fields": {"id_number": "T003", "region": "Mbeya", "district": "Mbeya Rural", "school": "Mbeya Secondary", "gender": "Female", "age_group": "45-54", "marital_status": "Divorsed", "education_level": "Master’S Degree", "forms_of_violence": "Verbal Abuse", "reporting_violence": true, "vulnerable_places": "Classroom", "right_to_discipline_child": true, "effective_handling_vac": "Weak", "training_received": "Yes"}}, {"model": "data_collection.parent", "pk": 1, "fields": {"id_number": "P001", "region": "Dar Es Salaam", "district": "Ilala", "school": "School A", "gender": "Male", "age_group": "35-45", "marital_status": "Married", "education_level": "Secondary", "forms_of_violence": "Bullying", "reporting_violence": true, "vulnerable_places": "Playground", "employment": "Employed", "physical_punishment": true, "believe_in_child_punishment": true, "effectiveness_positive_punishment": "Effective", "child_comforting": true, "impose_rules_to_child": true, "set_rules_with_child": false}}, {"model": "data_collection.parent", "pk": 2, "fields": {"id_number": "P002", "region": "Dar Es Salaam", "district": "Kinondoni", "school": "School B", "gender": "Female", "age_group": "30-40", "marital_status": "Single", "education_level": "Bachelor", "forms_of_violence": "Harassment", "reporting_violence": false, "vulnerable_places": "Classroom", "employment": "Self-Employed", "physical_punishment": false, "believe_in_child_punishment": false, "effectiveness_positive_punishment": "Weak", "child_comforting": true, "impose_rules_to_child": false, "set_rules_with_child": true}}, {"model": "data_collection.parent", "pk": 3, "fields": {"id_number": "P003", "region": "Kigoma", "district": "Kasulu", "school": "Kasulu Primary", "gender": "Female", "age_group": "45-54", "marital_status": "Widowed", "education_level": "Diploma", "forms_of_violence": "Sexual Harassment", "reporting_violence": false, "vulnerable_places": "Toilets", "employment": "Employed", "physical_punishment": true, "believe_in_child_punishment": true, "effectiveness_positive_punishment": "Effective", "child_comforting": false, "impose_rules_to_child": true, "set_rules_with_child": false}}, {"model": "indicators.indicator", "pk": 1, "fields": {"name": "Numbers of Meeting Held", "indicator_type": "input", "target_value": 3, "actual_value": 2, "description": "", "proof_document": "indicator_proofs/policy_report_8.pdf"}}, {"model": "settings.customuser", "pk": 1, "fields": {"password": "pbkdf2_sha256$1200000$lJZgQ6uXPD9Wwu6YHfbhYy$coYdT0TOjfogkYuXQ2MsthFWKyDDyEbWDKp6wocvCVo=", "last_login": "2026-02-25T09:22:37.306Z", "is_superuser": true, "username": "fawetz", "first_name": "", "last_name": "", "email": "fawetanzania836@gmail.com", "is_staff": true, "is_active": true, "date_joined": "2026-02-24T10:30:08.971Z", "role": "Admin", "groups": [], "user_permissions": []}}, {"model": "settings.customuser", "pk": 2, "fields": {"password": "pbkdf2_sha256$1200000$tzlOpwz5ay9Dp0jVYGYAJm$fZvxxhc8nVbFKHEb0PziP7b7Q3ecZx/6C3oI5HXkr5U=", "last_login": "2026-02-25T08:52:31.754Z", "is_superuser": false, "username": "data", "first_name": "", "last_name": "", "email": "data@fawe.com", "is_staff": false, "is_active": true, "date_joined": "2026-02-24T14:33:53.820Z", "role": "DataEntry", "groups": [], "user_permissions": []}}]
